tqt/__init__.py
tqt/__version__.py
tqt/config.py
tqt/fused_config.py
tqt/utils.py
tqt/wrapper.py
tqt/analyse/__init__.py
tqt/analyse/cos.py
tqt/analyse/kl.py
tqt/fold/__init__.py
tqt/fold/convbn.py
tqt/fold/convbnact.py
tqt/fold/fold_config.py
tqt/fold/fold_op.py
tqt/fold/foldmodule.py
tqt/fold/sabn.py
tqt/fold/sabnact.py
tqt/fold/sharequant.py
tqt/fold/utils.py
tqt/function/__init__.py
tqt/function/_utils.py
tqt/function/activation.py
tqt/function/adder.py
tqt/function/batchnorm.py
tqt/function/conv.py
tqt/function/linear.py
tqt/function/number.py
tqt/function/extra/__init__.py
tqt/function/extra/adder.py
tqt/function/extra/seconv.py
tqt/threshold/__init__.py
tqt/threshold/hook.py
tqt/threshold/ignore.py
tqt/threshold/init.py
tqt/threshold/kl.py
tqt/threshold/max.py
tqt/threshold/sd.py
tqt-1.0.2.dist-info/LICENSE
tqt-1.0.2.dist-info/METADATA
tqt-1.0.2.dist-info/WHEEL
tqt-1.0.2.dist-info/top_level.txt
tqt-1.0.2.dist-info/RECORD
